{"title":"my sister","slug":"my-sister","date":"2018-05-15T02:27:58.000Z","updated":"2018-05-15T02:32:03.560Z","comments":true,"path":"api/articles/my-sister.json","photos":[],"link":"","excerpt":null,"covers":null,"content":"<h3 id=\"Create-a-new-post\"><a href=\"#Create-a-new-post\" class=\"headerlink\" title=\"Create a new post\"></a>Create a new post</h3><p>记录一下这是来到github上的第一天<br><code>`</code></p>\n<p>More info: <a href=\"https://hexo.io/docs/writing.html\" target=\"_blank\" rel=\"noopener\">Writing</a></p>\n","categories":[],"tags":[]}